LICENSE.md
MANIFEST.in
README.md
pyproject.toml
setup.cfg
setup.py
conan/__init__.py
conan/errors.py
conan/api/__init__.py
conan/api/conan_api.py
conan/api/input.py
conan/api/output.py
conan/api/model/__init__.py
conan/api/model/list.py
conan/api/model/refs.py
conan/api/model/remote.py
conan/api/subapi/__init__.py
conan/api/subapi/audit.py
conan/api/subapi/cache.py
conan/api/subapi/command.py
conan/api/subapi/config.py
conan/api/subapi/download.py
conan/api/subapi/export.py
conan/api/subapi/graph.py
conan/api/subapi/install.py
conan/api/subapi/list.py
conan/api/subapi/local.py
conan/api/subapi/lockfile.py
conan/api/subapi/new.py
conan/api/subapi/profiles.py
conan/api/subapi/remotes.py
conan/api/subapi/remove.py
conan/api/subapi/report.py
conan/api/subapi/upload.py
conan/api/subapi/workspace.py
conan/cli/__init__.py
conan/cli/args.py
conan/cli/cli.py
conan/cli/command.py
conan/cli/exit_codes.py
conan/cli/commands/__init__.py
conan/cli/commands/audit.py
conan/cli/commands/build.py
conan/cli/commands/cache.py
conan/cli/commands/config.py
conan/cli/commands/create.py
conan/cli/commands/download.py
conan/cli/commands/editable.py
conan/cli/commands/export.py
conan/cli/commands/export_pkg.py
conan/cli/commands/graph.py
conan/cli/commands/inspect.py
conan/cli/commands/install.py
conan/cli/commands/list.py
conan/cli/commands/lock.py
conan/cli/commands/new.py
conan/cli/commands/pkglist.py
conan/cli/commands/profile.py
conan/cli/commands/remote.py
conan/cli/commands/remove.py
conan/cli/commands/report.py
conan/cli/commands/require.py
conan/cli/commands/run.py
conan/cli/commands/search.py
conan/cli/commands/source.py
conan/cli/commands/test.py
conan/cli/commands/upload.py
conan/cli/commands/version.py
conan/cli/commands/workspace.py
conan/cli/formatters/__init__.py
conan/cli/formatters/audit/__init__.py
conan/cli/formatters/audit/vulnerabilities.py
conan/cli/formatters/graph/__init__.py
conan/cli/formatters/graph/build_order_html.py
conan/cli/formatters/graph/graph.py
conan_server.egg-info/PKG-INFO
conan_server.egg-info/SOURCES.txt
conan_server.egg-info/dependency_links.txt
conan_server.egg-info/entry_points.txt
conan_server.egg-info/requires.txt
conan_server.egg-info/top_level.txt
